odoo/addons/account_invoice_uom_column/README.rst
odoo/addons/account_invoice_uom_column/__init__.py
odoo/addons/account_invoice_uom_column/__manifest__.py
odoo/addons/account_invoice_uom_column/i18n/fr.po
odoo/addons/account_invoice_uom_column/readme/CONTRIBUTORS.rst
odoo/addons/account_invoice_uom_column/readme/DESCRIPTION.rst
odoo/addons/account_invoice_uom_column/reports/report_account_invoice.xml
odoo/addons/account_invoice_uom_column/static/description/1_without_module.png
odoo/addons/account_invoice_uom_column/static/description/2_with_module.png
odoo/addons/account_invoice_uom_column/static/description/icon.png
odoo/addons/account_invoice_uom_column/static/description/index.html
odoo12_addon_account_invoice_uom_column-12.0.1.0.1.99.dev1.dist-info/METADATA
odoo12_addon_account_invoice_uom_column-12.0.1.0.1.99.dev1.dist-info/WHEEL
odoo12_addon_account_invoice_uom_column-12.0.1.0.1.99.dev1.dist-info/top_level.txt
odoo12_addon_account_invoice_uom_column-12.0.1.0.1.99.dev1.dist-info/RECORD
